{
  "hash": "c37fca0e",
  "browserHash": "1ebd6023",
  "optimized": {
    "vue": {
      "src": "../../../../node_modules/vue/dist/vue.runtime.esm-bundler.js",
      "file": "vue.js",
      "fileHash": "8a83e92c",
      "needsInterop": false
    },
    "vitepress > @vue/devtools-api": {
      "src": "../../../../node_modules/@vue/devtools-api/lib/esm/index.js",
      "file": "vitepress___@vue_devtools-api.js",
      "fileHash": "020ea368",
      "needsInterop": false
    },
    "vitepress > minisearch": {
      "src": "../../../../node_modules/minisearch/dist/es/index.js",
      "file": "vitepress___minisearch.js",
      "fileHash": "dbe0b082",
      "needsInterop": false
    },
    "canvas": {
      "src": "../../../../node_modules/canvas/browser.js",
      "file": "canvas.js",
      "fileHash": "d36e5826",
      "needsInterop": true
    },
    "path2d-polyfill": {
      "src": "../../../../node_modules/path2d-polyfill/dist/path2d-polyfill.dev.js",
      "file": "path2d-polyfill.js",
      "fileHash": "c2b39e08",
      "needsInterop": true
    },
    "gitalk": {
      "src": "../../../../node_modules/gitalk/dist/gitalk.js",
      "file": "gitalk.js",
      "fileHash": "45811484",
      "needsInterop": true
    }
  },
  "chunks": {
    "chunk-76J2PTFD": {
      "file": "chunk-76J2PTFD.js"
    }
  }
}